mexc/__init__.py
mexc/__init__.pyi
mexc/_mexc.py
mexc/core/__init__.py
mexc/core/__init__.pyi
mexc/core/exc.py
mexc/core/types.py
mexc/core/util.py
mexc/core/validation.py
mexc/core/http/__init__.py
mexc/core/http/__init__.pyi
mexc/core/http/client.py
mexc/core/ws/__init__.py
mexc/core/ws/__init__.pyi
mexc/core/ws/base.py
mexc/futures/__init__.py
mexc/futures/__init__.pyi
mexc/futures/_futures.py
mexc/futures/core/__init__.py
mexc/futures/core/__init__.pyi
mexc/futures/core/auth.py
mexc/futures/core/util.py
mexc/futures/market_data/__init__.py
mexc/futures/market_data/__init__.pyi
mexc/futures/market_data/_market_data.py
mexc/futures/market_data/candles.py
mexc/futures/market_data/contract_info.py
mexc/futures/market_data/depth.py
mexc/futures/market_data/funding_rate.py
mexc/futures/market_data/funding_rate_history.py
mexc/futures/streams/__init__.py
mexc/futures/streams/__init__.pyi
mexc/futures/streams/_streams.py
mexc/futures/streams/core/__init__.py
mexc/futures/streams/core/__init__.pyi
mexc/futures/streams/core/auth.py
mexc/futures/streams/core/client.py
mexc/futures/streams/core/streams_rpc.py
mexc/futures/streams/market/__init__.py
mexc/futures/streams/market/__init__.pyi
mexc/futures/streams/market/_market.py
mexc/futures/streams/market/tickers.py
mexc/futures/streams/user/__init__.py
mexc/futures/streams/user/__init__.pyi
mexc/futures/streams/user/_user.py
mexc/futures/streams/user/my_trades.py
mexc/futures/trading/__init__.py
mexc/futures/trading/__init__.pyi
mexc/futures/trading/_trading.py
mexc/futures/user_data/__init__.py
mexc/futures/user_data/__init__.pyi
mexc/futures/user_data/_user_data.py
mexc/futures/user_data/assets.py
mexc/futures/user_data/my_funding_history.py
mexc/futures/user_data/my_trades.py
mexc/futures/user_data/positions.py
mexc/sdk/__init__.py
mexc/sdk/__init__.pyi
mexc/sdk/_sdk.py
mexc/sdk/core/__init__.py
mexc/sdk/core/__init__.pyi
mexc/sdk/core/exc.py
mexc/sdk/core/mixin.py
mexc/sdk/core/naming.py
mexc/sdk/core/parsing.py
mexc_trading_sdk-0.1.12.dist-info/METADATA
mexc_trading_sdk-0.1.12.dist-info/WHEEL
mexc_trading_sdk-0.1.12.dist-info/top_level.txt
mexc_trading_sdk-0.1.12.dist-info/RECORD
