Metadata-Version: 2.4
Name: mexc-trading-sdk
Version: 0.1.12
Summary: The unofficial MEXC API SDK, by Tribulnation. Compatible with Trading SDK.
Author-email: Marcel Claramunt <marcel@tribulnation.com>
Project-URL: repo, https://github.com/tribulnation/mexc.git
Requires-Python: >=3.10
Requires-Dist: lazy-loader
Requires-Dist: httpx
Requires-Dist: pydantic
Requires-Dist: protobuf==3.20
Requires-Dist: websockets
Provides-Extra: sdk
Requires-Dist: trading-sdk; extra == "sdk"
Provides-Extra: orjson
Requires-Dist: orjson; extra == "orjson"
